mplserialscope/__init__.py
mplserialscope/animate.py
mplserialscope/blitting.py
mplserialscope-0.1.1.dist-info/LICENSE
mplserialscope-0.1.1.dist-info/METADATA
mplserialscope-0.1.1.dist-info/WHEEL
mplserialscope-0.1.1.dist-info/top_level.txt
mplserialscope-0.1.1.dist-info/RECORD
